README.rst
setup.cfg
setup.py
testdimensions.py
testdimensions.egg-info/PKG-INFO
testdimensions.egg-info/SOURCES.txt
testdimensions.egg-info/dependency_links.txt
testdimensions.egg-info/top_level.txt