Metadata-Version: 1.1
Name: testdimensions
Version: 0.0.1
Summary: Multi-dimensional parameterized tests for Pytest and Nose
Home-page: https://github.com/akaihola/testdimensions
Author: Antti Kaihola
Author-email: antti dot kaihola at eniram and finally fi for finland
License: FreeBSD
Platform: UNKNOWN
Classifier: Programming Language :: Python
Classifier: Programming Language :: Python :: 2.7
Classifier: Programming Language :: Python :: 3.3
Classifier: Programming Language :: Python :: 3.4
Classifier: Programming Language :: Python :: 3.5
Classifier: License :: OSI Approved :: BSD License
